setup.cfg
setup.py
ntlm/HTTPNtlmAuthHandler.py
ntlm/U32.py
ntlm/__init__.py
ntlm/des.py
ntlm/des_c.py
ntlm/des_data.py
ntlm/ntlm.py
python_ntlm_fixed.egg-info/PKG-INFO
python_ntlm_fixed.egg-info/SOURCES.txt
python_ntlm_fixed.egg-info/dependency_links.txt
python_ntlm_fixed.egg-info/entry_points.txt
python_ntlm_fixed.egg-info/not-zip-safe
python_ntlm_fixed.egg-info/requires.txt
python_ntlm_fixed.egg-info/top_level.txt