Metadata-Version: 1.0
Name: python-ntlm-fixed
Version: 1.0
Summary: Python library that provides NTLM support, including an authentication handler for urllib2 (with fixed hashlib dependency).
Home-page: http://pypi.python.org/pypi/python-ntlm-fixed
Author: Matthijs Mullender
Author-email: info@zopyx.com
License: UNKNOWN
Platform: UNKNOWN
